croppy/__init__.py
croppy/pixval_tools.py
croppy/plant_info_tools.py
croppy-0.1.0.1.9.dist-info/LICENSE
croppy-0.1.0.1.9.dist-info/METADATA
croppy-0.1.0.1.9.dist-info/WHEEL
croppy-0.1.0.1.9.dist-info/top_level.txt
croppy-0.1.0.1.9.dist-info/RECORD
