Metadata-Version: 2.1
Name: croppy
Version: 0.1.0.1.9
Summary: A crop insurance specific package
Home-page: https://github.com/surasakcho/croppy
Author: Surasak Choedpasuporn
Author-email: surasak.cho@gmail.com
License: UNKNOWN
Platform: UNKNOWN
Classifier: Programming Language :: Python :: 3
Classifier: License :: OSI Approved :: MIT License
Classifier: Operating System :: OS Independent
Requires-Python: >=3.6
